LICENSE.TXT
MANIFEST.in
README.rst
setup.cfg
setup.py
mapproxy_hips/__init__.py
mapproxy_hips/pluginmodule.py
mapproxy_hips.egg-info/PKG-INFO
mapproxy_hips.egg-info/SOURCES.txt
mapproxy_hips.egg-info/dependency_links.txt
mapproxy_hips.egg-info/entry_points.txt
mapproxy_hips.egg-info/not-zip-safe
mapproxy_hips.egg-info/requires.txt
mapproxy_hips.egg-info/top_level.txt
mapproxy_hips/config/__init__.py
mapproxy_hips/config/hips_service_configuration.py
mapproxy_hips/config/hips_source_configuration.py
mapproxy_hips/script/__init__.py
mapproxy_hips/script/hipsallsky.py
mapproxy_hips/script/hipsseed.py
mapproxy_hips/service/__init__.py
mapproxy_hips/service/demo_extra.py
mapproxy_hips/service/hips.py
mapproxy_hips/service/templates/demo/demo_hips_template.html
mapproxy_hips/service/templates/demo/hips_demo.html
mapproxy_hips/source/__init__.py
mapproxy_hips/source/hips.py
mapproxy_hips/util/__init__.py
mapproxy_hips/util/hips.py
mapproxy_hips/util/resampling.py