Metadata-Version: 2.1
Name: mapproxy-hips
Version: 0.2.0
Summary: Plugin for MapProxy adding HIPS capabilities
Home-page: https://github.com/rouault/mapproxy_hips
Author: Even Rouault
Author-email: even.rouault@spatialys.com
License: MIT
Platform: UNKNOWN
Classifier: Operating System :: OS Independent
Classifier: Programming Language :: Python :: 2.7
Classifier: Programming Language :: Python :: 3.6
Classifier: Programming Language :: Python :: 3.7
Classifier: Programming Language :: Python :: 3.8
Classifier: Programming Language :: Python :: 3.9
Classifier: Programming Language :: Python :: 3.10
Classifier: Topic :: Internet :: Proxy Servers
Classifier: Topic :: Internet :: WWW/HTTP :: WSGI
Classifier: Topic :: Scientific/Engineering :: GIS
Requires-Python: >=3.7
License-File: LICENSE.TXT
